{"total":28,"rows":[
  {"id":1,"severity":"3","function":"diff()","operator":">=","value":"5","description":"","status":"0","modify_time":"2016/08/16 10:11"},
  {"id":2,"severity":"4","function":"diff()","operator":"<","value":"51","description":"","status":"0","modify_time":"2016/08/16 10:11"},
  {"id":3,"severity":"5","function":"diff()","operator":"==","value":"15","description":"","status":"0","modify_time":"2016/08/16 10:11"},
  {"id":4,"severity":"6","function":"diff()","operator":"!=","value":"25","description":"","status":"0","modify_time":"2016/08/16 10:11"}
]}
